gnnepcsaftcli/__init__.py
gnnepcsaftcli/main.py
gnnepcsaftcli-0.5.2.dist-info/entry_points.txt
gnnepcsaftcli-0.5.2.dist-info/METADATA
gnnepcsaftcli-0.5.2.dist-info/WHEEL
gnnepcsaftcli-0.5.2.dist-info/RECORD
