Metadata-Version: 2.3
Name: gnnepcsaftcli
Version: 0.5.2
Summary: CLI for GNNePCSAFT
Author: wildsonbbl
Author-email: wil_bbl@hotmail.com
Requires-Python: >=3.10
Classifier: Programming Language :: Python :: 3
Classifier: Programming Language :: Python :: 3.10
Classifier: Programming Language :: Python :: 3.11
Classifier: Programming Language :: Python :: 3.12
Classifier: Programming Language :: Python :: 3.13
Requires-Dist: gnnepcsaft-mcp-server (>=0.4)
Requires-Dist: onnxruntime (>=1.20.1,<2.0.0)
Requires-Dist: rdkit (>=2024.9.4,<2025.0.0)
Requires-Dist: typer (>=0.15.1,<0.16.0)
